iae/__init__.py
iae/preprocessing.py
iae/supervised.py
iae/unsupervised.py
iae_i/__init__.py
iae_i/preprocessing.py
iae_i/supervised.py
iae_i/unsupervised.py
iae_i-0.1.dist-info/LICENSE
iae_i-0.1.dist-info/METADATA
iae_i-0.1.dist-info/WHEEL
iae_i-0.1.dist-info/top_level.txt
iae_i-0.1.dist-info/RECORD
