Metadata-Version: 2.1
Name: iae-i
Version: 0.1
Summary: A collection of personal utility functions
Home-page: https://github.com/yourusername/mypackage
Author: Your Name
Author-email: your.email@example.com
Classifier: Programming Language :: Python :: 3
Classifier: License :: OSI Approved :: MIT License
Classifier: Operating System :: OS Independent
Requires-Python: >=3.6
License-File: LICENSE
